openadapt_capture/__init__.py
openadapt_capture/audio.py
openadapt_capture/browser_bridge.py
openadapt_capture/browser_events.py
openadapt_capture/capture.py
openadapt_capture/cli.py
openadapt_capture/comparison.py
openadapt_capture/config.py
openadapt_capture/events.py
openadapt_capture/input.py
openadapt_capture/processing.py
openadapt_capture/recorder.py
openadapt_capture/stats.py
openadapt_capture/storage.py
openadapt_capture/video.py
openadapt_capture/visualize/__init__.py
openadapt_capture/visualize/demo.py
openadapt_capture/visualize/html.py
openadapt_capture/visualize/overlays.py
openadapt_capture-0.2.0.dist-info/METADATA
openadapt_capture-0.2.0.dist-info/WHEEL
openadapt_capture-0.2.0.dist-info/entry_points.txt
openadapt_capture-0.2.0.dist-info/RECORD
