Metadata-Version: 2.4
Name: openadapt-capture
Version: 0.2.0
Summary: GUI interaction capture - platform-agnostic event streams with time-aligned media
Project-URL: Homepage, https://github.com/OpenAdaptAI/openadapt-capture
Project-URL: Repository, https://github.com/OpenAdaptAI/openadapt-capture
Author-email: "MLDSAI Inc." <richard@openadapt.ai>
License-Expression: MIT
Keywords: automation,capture,events,gui,rpa
Classifier: Development Status :: 2 - Pre-Alpha
Classifier: Intended Audience :: Developers
Classifier: License :: OSI Approved :: MIT License
Classifier: Programming Language :: Python :: 3
Classifier: Programming Language :: Python :: 3.10
Classifier: Programming Language :: Python :: 3.11
Classifier: Programming Language :: Python :: 3.12
Classifier: Topic :: Software Development :: Libraries :: Python Modules
Requires-Python: >=3.10
Requires-Dist: av>=10.0.0
Requires-Dist: fire>=0.7.1
Requires-Dist: mss>=6.0.0
Requires-Dist: openai>=2.11.0
Requires-Dist: pillow>=9.0.0
Requires-Dist: pydantic-settings>=2.12.0
Requires-Dist: pydantic>=2.0.0
Requires-Dist: pynput>=1.7.0
Requires-Dist: sounddevice>=0.5.3
Requires-Dist: soundfile>=0.13.1
Requires-Dist: websockets>=12.0
Provides-Extra: all
Requires-Dist: faster-whisper>=1.1.0; extra == 'all'
Requires-Dist: openadapt-privacy>=0.1.0; extra == 'all'
Requires-Dist: openai-whisper>=20230314; extra == 'all'
Provides-Extra: dev
Requires-Dist: matplotlib>=3.5.0; extra == 'dev'
Requires-Dist: numpy>=1.21.0; extra == 'dev'
Requires-Dist: pytest-asyncio>=0.23.0; extra == 'dev'
Requires-Dist: pytest-cov>=4.0.0; extra == 'dev'
Requires-Dist: pytest>=7.0.0; extra == 'dev'
Requires-Dist: ruff>=0.1.0; extra == 'dev'
Provides-Extra: privacy
Requires-Dist: openadapt-privacy>=0.1.0; extra == 'privacy'
Provides-Extra: transcribe
Requires-Dist: openai-whisper>=20230314; extra == 'transcribe'
Provides-Extra: transcribe-fast
Requires-Dist: faster-whisper>=1.1.0; extra == 'transcribe-fast'
